pax/__init__.py
pax/autograd.py
pax/modules.py
pax/optim.py
pax/optim_schedules.py
pax/tree_util.py
pax/utils.py
pax/tasks/__init__.py
pax/tasks/registry.py
pax/tasks/test.py
pax/tasks/datasets/__init__.py
pax/tasks/datasets/api.py
pax/tasks/datasets/deepobs.py
pax/tasks/datasets/libsvm.py
pax/tasks/datasets/torchvision.py
pax/tasks/datasets/utils.py
pax/tasks/models/__init__.py
pax/tasks/models/api.py
pax/tasks/models/basic.py
pax/tasks/models/deepobs.py
pax/tasks/models/resnet20.py
pax/tasks/models/timm.py
pax/tasks/models/torchvision.py
pax/tasks/tasks/__init__.py
pax/tasks/tasks/api.py
pax/tasks/tasks/classification.py
pax/tasks/tasks/deepobs.py
pax/utils/__init__.py
pax/utils/accumulators.py
pax/utils/call_stack.py
paxlib-0.3.5.dist-info/LICENSE
paxlib-0.3.5.dist-info/METADATA
paxlib-0.3.5.dist-info/WHEEL
paxlib-0.3.5.dist-info/top_level.txt
paxlib-0.3.5.dist-info/RECORD
